wikimore/__init__.py
wikimore/app.py
wikimore/cache.py
wikimore/static/css/dark-mode.css
wikimore/static/css/style.css
wikimore/templates/article.html
wikimore/templates/base.html
wikimore/templates/home.html
wikimore/templates/search_results.html
wikimore-0.1.16.dist-info/METADATA
wikimore-0.1.16.dist-info/WHEEL
wikimore-0.1.16.dist-info/entry_points.txt
wikimore-0.1.16.dist-info/licenses/LICENSE
wikimore-0.1.16.dist-info/RECORD
