Metadata-Version: 2.4
Name: wikimore
Version: 0.1.16
Summary: A simple frontend for Wikimedia wikis
Project-URL: Homepage, https://git.private.coffee/privatecoffee/wikimore
Project-URL: Bug Tracker, https://git.private.coffee/privatecoffee/wikimore/issues
Project-URL: Source Code, https://git.private.coffee/privatecoffee/wikimore
Author-email: "Private.coffee Team" <support@private.coffee>
License: Copyright (c) 2024 Private.coffee Team <support@private.coffee>
License-File: LICENSE
Classifier: License :: OSI Approved :: MIT License
Classifier: Operating System :: OS Independent
Classifier: Programming Language :: Python :: 3
Requires-Python: >=3.10
Requires-Dist: bs4
Requires-Dist: flask
Requires-Dist: flask-caching
Provides-Extra: redis
Requires-Dist: redis; extra == 'redis'
